carconnectivity_mqtt/__init__.py
carconnectivity_mqtt/carconnectivity_mqtt_base.py
carconnectivity_plugin_mqtt-0.9.2.dist-info/licenses/LICENSE
carconnectivity_plugins/mqtt/__init__.py
carconnectivity_plugins/mqtt/_version.py
carconnectivity_plugins/mqtt/mqtt_client.py
carconnectivity_plugins/mqtt/plugin.py
carconnectivity_plugins/mqtt/ui/plugin_ui.py
carconnectivity_plugins/mqtt/ui/templates/mqtt/status.html
carconnectivity_plugin_mqtt-0.9.2.dist-info/METADATA
carconnectivity_plugin_mqtt-0.9.2.dist-info/WHEEL
carconnectivity_plugin_mqtt-0.9.2.dist-info/entry_points.txt
carconnectivity_plugin_mqtt-0.9.2.dist-info/top_level.txt
carconnectivity_plugin_mqtt-0.9.2.dist-info/RECORD
