Metadata-Version: 2.4
Name: carconnectivity-plugin-mqtt
Version: 0.9.2
Summary: CarConnectivity plugin for publishing data to MQTT
Author: Till Steinbach
License-Expression: MIT
Classifier: Development Status :: 3 - Alpha
Classifier: Intended Audience :: End Users/Desktop
Classifier: Intended Audience :: System Administrators
Classifier: Programming Language :: Python :: 3.9
Classifier: Programming Language :: Python :: 3.10
Classifier: Programming Language :: Python :: 3.11
Classifier: Programming Language :: Python :: 3.12
Classifier: Programming Language :: Python :: 3.13
Classifier: Programming Language :: Python :: 3.14
Classifier: Topic :: Utilities
Classifier: Topic :: System :: Monitoring
Classifier: Topic :: Home Automation
Requires-Python: >=3.9
License-File: LICENSE
Requires-Dist: carconnectivity>=0.11.6
Requires-Dist: paho-mqtt~=2.1.0
Requires-Dist: python-dateutil~=2.9.0
Provides-Extra: connectors
Requires-Dist: carconnectivity-connector-volkswagen>=0.10.2; extra == "connectors"
Requires-Dist: carconnectivity-connector-skoda>=0.11.8; extra == "connectors"
Requires-Dist: carconnectivity-connector-seatcupra>=0.5.2; extra == "connectors"
Requires-Dist: carconnectivity-connector-tronity>=0.7.1; extra == "connectors"
Provides-Extra: plugins
Requires-Dist: carconnectivity-plugin-mqtt_homeassistant>=0.6.2; extra == "plugins"
Requires-Dist: carconnectivity-plugin-abrp>=0.8.1; extra == "plugins"
Requires-Dist: carconnectivity-plugin-homekit>=0.7.4; extra == "plugins"
Requires-Dist: carconnectivity-plugin-webui>=0.7.1; extra == "plugins"
Requires-Dist: carconnectivity-plugin-database>=0.4.2; extra == "plugins"
Provides-Extra: homeassistant
Requires-Dist: carconnectivity-plugin-mqtt_homeassistant>=0.6.1; extra == "homeassistant"
Provides-Extra: all
Requires-Dist: carconnectivity-plugin-mqtt[connectors,plugins]; extra == "all"
Dynamic: license-file
